[
    {
        "attributes": {
            "description": "",
            "kibanaSavedObjectMeta": {
                "searchSourceJSON": "{\"query\":{\"language\":\"lucene\",\"query\":\"\"},\"filter\":[{\"$state\":{\"store\":\"appState\"},\"meta\":{\"alias\":null,\"disabled\":false,\"key\":\"name.keyword\",\"negate\":false,\"params\":{\"query\":\"Insights RBAC API perf test\",\"type\":\"phrase\"},\"type\":\"phrase\",\"value\":\"Insights RBAC API perf test\",\"indexRefName\":\"kibanaSavedObjectMeta.searchSourceJSON.filter[0].meta.index\"},\"query\":{\"match\":{\"name.keyword\":{\"query\":\"Insights RBAC API perf test\",\"type\":\"phrase\"}}}}],\"indexRefName\":\"kibanaSavedObjectMeta.searchSourceJSON.index\"}"
            },
            "title": "Insights RBAC runs info",
            "uiStateJSON": "{\"vis\":{\"params\":{\"sort\":{\"columnIndex\":null,\"direction\":null}}}}",
            "version": 1,
            "visState": "{\"title\":\"Insights RBAC runs info\",\"type\":\"table\",\"params\":{\"perPage\":10,\"showMetricsAtAllLevels\":false,\"showPartialRows\":false,\"showTotal\":false,\"sort\":{\"columnIndex\":null,\"direction\":null},\"totalFunc\":\"sum\"},\"aggs\":[{\"id\":\"6\",\"enabled\":true,\"type\":\"top_hits\",\"schema\":\"metric\",\"params\":{\"field\":\"parameters.cluster.pods.rbac.commit.id.keyword\",\"aggregate\":\"concat\",\"size\":1,\"sortField\":\"started\",\"sortOrder\":\"desc\",\"customLabel\":\"Git commit\"}},{\"id\":\"4\",\"enabled\":true,\"type\":\"max\",\"schema\":\"metric\",\"params\":{\"field\":\"parameters.test.duration\",\"customLabel\":\"Test duration [s]\"}},{\"id\":\"5\",\"enabled\":true,\"type\":\"top_hits\",\"schema\":\"metric\",\"params\":{\"field\":\"parameters.cluster.pods.rbac.count.keyword\",\"aggregate\":\"concat\",\"size\":1,\"sortField\":\"started\",\"sortOrder\":\"desc\",\"customLabel\":\"RBAC pods\"}},{\"id\":\"7\",\"enabled\":true,\"type\":\"top_hits\",\"schema\":\"metric\",\"params\":{\"field\":\"parameters.cluster.rbac.db_hostname.keyword\",\"aggregate\":\"concat\",\"size\":1,\"sortField\":\"started\",\"sortOrder\":\"desc\",\"customLabel\":\"RBAC DB hostname\"}},{\"id\":\"9\",\"enabled\":true,\"type\":\"top_hits\",\"schema\":\"metric\",\"params\":{\"field\":\"result.keyword\",\"aggregate\":\"concat\",\"size\":1,\"sortField\":\"started\",\"sortOrder\":\"desc\",\"customLabel\":\"Result\"}},{\"id\":\"8\",\"enabled\":true,\"type\":\"top_hits\",\"schema\":\"metric\",\"params\":{\"field\":\"golden.keyword\",\"aggregate\":\"concat\",\"size\":1,\"sortField\":\"started\",\"sortOrder\":\"desc\",\"customLabel\":\"Golden?\"}},{\"id\":\"1\",\"enabled\":true,\"type\":\"top_hits\",\"schema\":\"metric\",\"params\":{\"field\":\"parameters.cluster.context.keyword\",\"aggregate\":\"concat\",\"size\":1,\"sortField\":\"started\",\"sortOrder\":\"desc\",\"customLabel\":\"Cluster\"}},{\"id\":\"3\",\"enabled\":true,\"type\":\"top_hits\",\"schema\":\"metric\",\"params\":{\"field\":\"results.jenkins.build_url.keyword\",\"aggregate\":\"concat\",\"size\":1,\"sortField\":\"started\",\"sortOrder\":\"desc\",\"customLabel\":\"Jenkins job\"}},{\"id\":\"2\",\"enabled\":true,\"type\":\"terms\",\"schema\":\"bucket\",\"params\":{\"field\":\"parameters.run.keyword\",\"size\":100,\"order\":\"desc\",\"orderBy\":\"_key\",\"otherBucket\":false,\"otherBucketLabel\":\"Other\",\"missingBucket\":false,\"missingBucketLabel\":\"Missing\",\"customLabel\":\"Test run ID\"}}]}"
        },
        "id": "8f187040-4cb0-11ea-bfca-3fb30f912ea8",
        "migrationVersion": {
            "visualization": "7.10.0"
        },
        "references": [
            {
                "id": "94bcc1d0-77d1-11ea-bfca-3fb30f912ea8",
                "name": "kibanaSavedObjectMeta.searchSourceJSON.index",
                "type": "index-pattern"
            },
            {
                "id": "94bcc1d0-77d1-11ea-bfca-3fb30f912ea8",
                "name": "kibanaSavedObjectMeta.searchSourceJSON.filter[0].meta.index",
                "type": "index-pattern"
            }
        ],
        "type": "visualization",
        "updated_at": "2021-06-21T21:14:50.783Z",
        "version": "WzU1OTczLDE0XQ=="
    }
]